[
  {
    "country": "UK",
    "english_name": "29 High Street",
    "product_type": "Perfume",
    "product_url": "https://www.lush.com/uk/en/p/29-high-street"
  },
  {
    "country": "UK",
    "english_name": "4:20pm",
    "product_type": "Perfume",
    "product_url": "https://www.lush.com/uk/en/p/420pm-perfume"
  },
  {
    "country": "UK",
    "english_name": "American Cream",
    "product_type": "Perfume",
    "product_url": "https://www.lush.com/uk/en/p/american-cream-perfume"
  },
  {
    "country": "UK",
    "english_name": "Alina",
    "product_type": "Perfume",
    "product_url": "https://www.lush.com/uk/en/p/alina-perfume"
  },
  {
    "country": "UK",
    "english_name": "The Bee's Knees",
    "product_type": "Perfume",
    "product_url": "https://www.lush.com/uk/en/p/the-bees-knees-perfume"
  },
  {
    "country": "UK",
    "english_name": "Chelsea Morning",
    "product_type": "Perfume",
    "product_url": "https://www.lush.com/uk/en/p/chelsea-morning-perfume"
  },
  {
    "country": "UK",
    "english_name": "Dirty",
    "product_type": "Perfume",
    "product_url": "https://www.lush.com/uk/en/p/dirty-perfume"
  },
  {
    "country": "UK",
    "english_name": "Fresh As",
    "product_type": "Perfume",
    "product_url": "https://www.lush.com/uk/en/p/fresh-as-perfume"
  },
  {
    "country": "UK",
    "english_name": "Lord Of Misrule",
    "product_type": "Perfume",
    "product_url": "https://www.lush.com/uk/en/p/lord-of-misrule-perfume"
  },
  {
    "country": "UK",
    "english_name": "Lust",
    "product_type": "Perfume",
    "product_url": "https://www.lush.com/uk/en/p/lust-perfume"
  },
  {
    "country": "UK",
    "english_name": "No Way to Say Goodbye",
    "product_type": "Perfume",
    "product_url": "https://www.lush.com/uk/en/p/no-way-to-say-goodbye-perfume"
  },
  {
    "country": "UK",
    "english_name": "Karma",
    "product_type": "Body Spray",
    "product_url": "https://www.lush.com/uk/en/p/karma-body-spray"
  },
  {
    "country": "UK",
    "english_name": "Dirty",
    "product_type": "Body Spray",
    "product_url": "https://www.lush.com/uk/en/p/dirty-body-spray"
  },
  {
    "country": "UK",
    "english_name": "Breath Of God",
    "product_type": "Body Spray",
    "product_url": "https://www.lush.com/uk/en/p/breath-of-god-body-spray"
  },
  {
    "country": "UK",
    "english_name": "Grass",
    "product_type": "Body Spray",
    "product_url": "https://www.lush.com/uk/en/p/grass-body-spray"
  },
  {
    "country": "UK",
    "english_name": "Chelsea Morning",
    "product_type": "Body Spray",
    "product_url": "https://www.lush.com/uk/en/p/chelsea-morning-body-spray"
  },
  {
    "country": "UK",
    "english_name": "Lord Of Misrule",
    "product_type": "Body Spray",
    "product_url": "https://www.lush.com/uk/en/p/lord-of-misrule-body-spray"
  },
  {
    "country": "UK",
    "english_name": "Vanillary",
    "product_type": "Body Spray",
    "product_url": "https://www.lush.com/uk/en/p/vanillary-body-spray"
  },
  {
    "country": "UK",
    "english_name": "Let The Good Times Roll",
    "product_type": "Body Spray",
    "product_url": "https://www.lush.com/uk/en/p/let-the-good-times-roll-body-spray"
  }
]